cubicweb_jqplot/__init__.py
cubicweb_jqplot/__pkginfo__.py
cubicweb_jqplot/views.py
cubicweb_jqplot/data/MIT-LICENSE.txt
cubicweb_jqplot/data/copyright.txt
cubicweb_jqplot/data/cubes.jqplot.css
cubicweb_jqplot/data/cubes.jqplot.ext.js
cubicweb_jqplot/data/cubes.jqplot.js
cubicweb_jqplot/data/icon_csv.gif
cubicweb_jqplot/data/icon_png.gif
cubicweb_jqplot/data/jquery.jqplot.css
cubicweb_jqplot/data/jquery.jqplot.js
cubicweb_jqplot/data/jquery.jqplot.min.css
cubicweb_jqplot/data/jquery.jqplot.min.js
cubicweb_jqplot/data/plugins/jqplot.BezierCurveRenderer.js
cubicweb_jqplot/data/plugins/jqplot.BezierCurveRenderer.min.js
cubicweb_jqplot/data/plugins/jqplot.barRenderer.js
cubicweb_jqplot/data/plugins/jqplot.barRenderer.min.js
cubicweb_jqplot/data/plugins/jqplot.blockRenderer.js
cubicweb_jqplot/data/plugins/jqplot.blockRenderer.min.js
cubicweb_jqplot/data/plugins/jqplot.bubbleRenderer.js
cubicweb_jqplot/data/plugins/jqplot.bubbleRenderer.min.js
cubicweb_jqplot/data/plugins/jqplot.canvasAxisLabelRenderer.js
cubicweb_jqplot/data/plugins/jqplot.canvasAxisLabelRenderer.min.js
cubicweb_jqplot/data/plugins/jqplot.canvasAxisTickRenderer.js
cubicweb_jqplot/data/plugins/jqplot.canvasAxisTickRenderer.min.js
cubicweb_jqplot/data/plugins/jqplot.canvasOverlay.js
cubicweb_jqplot/data/plugins/jqplot.canvasOverlay.min.js
cubicweb_jqplot/data/plugins/jqplot.canvasTextRenderer.js
cubicweb_jqplot/data/plugins/jqplot.canvasTextRenderer.min.js
cubicweb_jqplot/data/plugins/jqplot.categoryAxisRenderer.js
cubicweb_jqplot/data/plugins/jqplot.categoryAxisRenderer.min.js
cubicweb_jqplot/data/plugins/jqplot.ciParser.js
cubicweb_jqplot/data/plugins/jqplot.ciParser.min.js
cubicweb_jqplot/data/plugins/jqplot.cursor.js
cubicweb_jqplot/data/plugins/jqplot.cursor.min.js
cubicweb_jqplot/data/plugins/jqplot.dateAxisRenderer.js
cubicweb_jqplot/data/plugins/jqplot.dateAxisRenderer.min.js
cubicweb_jqplot/data/plugins/jqplot.donutRenderer.js
cubicweb_jqplot/data/plugins/jqplot.donutRenderer.min.js
cubicweb_jqplot-1.1.0.dist-info/METADATA
cubicweb_jqplot-1.1.0.dist-info/WHEEL
cubicweb_jqplot-1.1.0.dist-info/entry_points.txt
cubicweb_jqplot-1.1.0.dist-info/top_level.txt
cubicweb_jqplot-1.1.0.dist-info/RECORD
